{
  "title": "UX Pilot - Superfast UX/UI Design with AI",
  "bodyText": "Try UX Pilot for Free\n25%\n50%\n75%\n100%\nDesktop\nDesktop HD\nTablet\nMobile\nW\nH\nMake it mine\nMade in UX Pilot\nComments\n\nSign in to comment\n\nSign in to view and add comments on this design.",
  "htmlSnippet": {
    "headings": [
      "Comments"
    ],
    "text": "Try UX Pilot for Free\n25%\n50%\n75%\n100%\nDesktop\nDesktop HD\nTablet\nMobile\nW\nH\nMake it mine\nMade in UX Pilot\nComments\n\nSign in to comment\n\nSign in to view and add comments on this design."
  }
}